logmatic/__init__.py
logmatic/log.py
logmatic/logger.py
logmatic/socket_logger.py
logmatic/utils/__init__.py
logmatic/utils/pather.py
logmatic/utils/truncate.py
logmatic-0.3.5.dist-info/METADATA
logmatic-0.3.5.dist-info/WHEEL
logmatic-0.3.5.dist-info/top_level.txt
logmatic-0.3.5.dist-info/RECORD
