Metadata-Version: 2.1
Name: logmatic
Version: 0.3.5
Summary: Basic logging wrapper for Python.
Home-page: https://github.com/krinj/logmatic
Author: Jakrin Juangbhanich
Author-email: juangbhanich.k@gmail.com
License: UNKNOWN
Platform: UNKNOWN
Classifier: Programming Language :: Python :: 3.6
Requires-Dist: python-dotenv
